[
	{
		"cmd": "help [command]",
		"desc": "Print a help message.",
		"path": "",
		"group": ""
	},
	{
		"cmd": "arch",
		"desc": "Operating system CPU architecture.",
		"path": "./lib/node_modules/@stdlib/os/arch/bin/cli",
		"group": "OS"
	},
	{
		"cmd": "bundle-pkg-list",
		"desc": "Bundle a list of packages into a single file.",
		"path": "./lib/node_modules/@stdlib/_tools/bundle/pkg-list/bin/cli",
		"group": "Tools"
	},
	{
		"cmd": "configdir",
		"desc": "Configuration directory path.",
		"path": "./lib/node_modules/@stdlib/os/configdir/bin/cli",
		"group": "OS"
	},
	{
		"cmd": "datasets",
		"desc": "Retrieve a dataset.",
		"path": "./lib/node_modules/@stdlib/datasets/bin/cli",
		"group": ""
	},
	{
		"cmd": "homedir",
		"desc": "Home directory path.",
		"path": "./lib/node_modules/@stdlib/os/homedir/bin/cli",
		"group": "OS"
	},
	{
		"cmd": "ls",
		"desc": "List package names.",
		"path": "./lib/node_modules/@stdlib/_tools/pkgs/names/bin/cli",
		"group": "Meta"
	},
	{
		"cmd": "ls-tree",
		"desc": "Show package tree.",
		"path": "./lib/node_modules/@stdlib/_tools/pkgs/tree/bin/cli",
		"group": "Meta"
	},
	{
		"cmd": "ns",
		"desc": "Print namespace.",
		"path": "./lib/node_modules/@stdlib/namespace/bin/cli",
		"group": "Meta"
	},
	{
		"cmd": "num-cpus",
		"desc": "Number of CPUs.",
		"path": "./lib/node_modules/@stdlib/os/num-cpus/bin/cli",
		"group": "OS"
	},
	{
		"cmd": "platform",
		"desc": "Platform.",
		"path": "./lib/node_modules/@stdlib/os/platform/bin/cli",
		"group": "OS"
	},
	{
		"cmd": "repl",
		"desc": "Start a REPL.",
		"path": "./lib/node_modules/@stdlib/repl/bin/cli",
		"group": ""
	},
	{
		"cmd": "sparkline",
		"desc": "Plot a sparkline.",
		"path": "./lib/node_modules/@stdlib/plot/sparklines/unicode/bin/cli",
		"group": "Plot"
	},
	{
		"cmd": "tmpdir",
		"desc": "Directory path for storing temporary files.",
		"path": "./lib/node_modules/@stdlib/os/tmpdir/bin/cli",
		"group": "OS"
	}
]
